[
    {
      "name": "Prithvi Saini",
      "email": "prithvisaini892@gmail.com"
    },
    {
      "name": "Susovan majumder",
      "email": ""
    },
    {
      "name": "Shruti Banerjee",
      "email": "shrutibanerjee2003@gmail.com"
    },
    {
      "name": "Shukla Keshri",
      "email": "shukla.roy96@gmail.com"
    },
    {
      "name": "Rahul Khuje",
      "email": "khuje.rahul@gmail.com"
    },
    {
      "name": "Sk shoaib",
      "email": "skshoaib2112@gmail.com"
    },
    {
      "name": "Debayan Mitra",
      "email": "itsdebayan55@gmail.com"
    },
    {
      "name": "Sourav Biswas",
      "email": "thisissouravbiswas@gmail.com"
    },
    {
      "name": "Tamal Paul",
      "email": ""
    },
    {
      "name": "Apurba Sekhar Misra",
      "email": "apurba.sekhar.misra@gmail.com"
    },
    {
      "name": "Vivek yadav",
      "email": "vivek90160@gmail.com"
    },
    {
      "name": "Farukh Ahmed sattar Khan",
      "email": "fk348151@gmail.com"
    },
    {
      "name": "Renuka Laxmikant Sarvade",
      "email": "renukasarvade2903@gmail.com"
    },
    {
      "name": "Rachana Sarkar",
      "email": "rachanasarkar587@gmail.com"
    },
    {
      "name": "ABHISHEK ANAND",
      "email": "abhishekanand8292@gmail.com"
    },
    {
      "name": "Kush Kumar",
      "email": ""
    },
    {
      "name": "Sainath nikam",
      "email": "sainathnikam1100@gmail.com"
    },
    {
      "name": "Pragathi S",
      "email": "dollypragathi465@gmail.com"
    },
    {
      "name": "Saumya singh",
      "email": "sgnsaum@gmail.com"
    },
    {
      "name": "Aparna",
      "email": ""
    },
    {
      "name": "RAJU KABIRAJ",
      "email": "rajukabiraj0412@gmail.com"
    },
    {
      "name": "Jyoti prakash",
      "email": "Pukun21jp@gmail.com"
    },
    {
      "name": "Bijit jana",
      "email": "bijitjana4@gmail.com"
    },
    {
      "name": "Bubai Das",
      "email": "dasb85516@gmail.com"
    },
    {
      "name": "Anil",
      "email": "m9652020659@gmail.com"
    },
    {
      "name": "Bikram Nanda",
      "email": "bikramnanda2751@gmail.com"
    },
    {
      "name": "Vishal Shrivastav",
      "email": "Vishalshrivasthav123@gmail.com"
    },
    {
      "name": "Subho Jana",
      "email": ""
    },
    {
      "name": "Wasim",
      "email": ""
    },
    {
      "name": "Amarjeet Vishwakarma",
      "email": "amar40jeet@gmail.com"
    },
    {
      "name": "Bhagyashree",
      "email": "bhagyashankre20@gmail.com"
    },
    {
      "name": "Samar Singh",
      "email": "somasingh889@gmail.com"
    },
    {
      "name": "Asra Shaikh",
      "email": "shaikhasra5555@gmail.com"
    },
    {
      "name": "A Vamshireddy",
      "email": "vamshireddyv19@gmail.com"
    },
    {
      "name": "Rahul",
      "email": "rahulwalker87@gmail.com"
    },
    {
      "name": "Saif Ali",
      "email": ""
    },
    {
      "name": "Manish gotmare",
      "email": "manish1999gotmare@gmail.com"
    },
    {
      "name": "Mohammad asim",
      "email": "asimquraishi1337@gmail.com"
    },
    {
      "name": "Chiranjit sarkar",
      "email": "schiranjit99@gmail.com"
    },
    {
      "name": "Saravana",
      "email": "ss5931570@gmail.com"
    },
    {
      "name": "Tahamid Sk",
      "email": ""
    },
    {
      "name": "SAMIR HASAN",
      "email": "hasansamir7777@gmail.com"
    },
    {
      "name": "Abhishek",
      "email": ""
    },
    {
      "name": "Durganand Chowdhury",
      "email": ""
    },
    {
      "name": "Rajkumar Kohel",
      "email": "rajkumarkohel@gmail.com"
    },
    {
      "name": "Mahendra",
      "email": ""
    },
    {
      "name": "Ashutosh Kumar Singh",
      "email": "singh.ashutosh8087@gmail.com"
    },
    {
      "name": "AISHANEE MUKJERJEE",
      "email": "aishaneemukherjee2003@gmail.com"
    },
    {
      "name": "Achismita Dey",
      "email": "achismitadey@gmail.com"
    },
    {
      "name": "Bilal",
      "email": "bk9806758@gmail.com"
    },
    {
      "name": "Sagar Kumar",
      "email": "sagarkr423@gmail.com"
    },
    {
      "name": "ChaudhariAbhaykumar rakeshbhai",
      "email": "abhaychaudhari09@gmail.com"
    },
    {
      "name": "Hiba Ansari",
      "email": ""
    },
    {
      "name": "Diyali Das",
      "email": "diyalidasdola@gmail.com"
    },
    {
      "name": "arindam sarkar",
      "email": ""
    },
    {
      "name": "Raja Kumar Yadav",
      "email": ""
    },
    {
      "name": "HIMANSHU PACHAURI",
      "email": "HIMANSHUPACHAURI089@GMAIL.COM"
    },
    {
      "name": "Bikash Maity",
      "email": "bikashmaity7214@gmail.com"
    },
    {
      "name": "Yuvraj",
      "email": ""
    },
    {
      "name": "Jaysurya T Sonawane",
      "email": "sameer.s.2568@gmail.com"
    },
    {
      "name": "Joy Sadhu",
      "email": ""
    },
    {
      "name": "Animesh Mukherjee",
      "email": "animeshmukherjee50937@gmail.com"
    },
    {
      "name": "Tejasswi Somnath Gunjal",
      "email": "teju13gunjal@gmail.com"
    },
    {
      "name": "Amsta",
      "email": "leeany321@gmail.com"
    },
    {
      "name": "Mihir sharma",
      "email": "mihirsharma9135@gmail.com"
    },
    {
      "name": "Halesh",
      "email": "haleshmangalur767@gmail.com"
    },
    {
      "name": "MAHESH JANGLE",
      "email": ""
    },
    {
      "name": "Ashutosh Kumar Mishra",
      "email": "ashucric2018@gmail.com"
    },
    {
      "name": "Haresh",
      "email": "haresh2197@gmail.com"
    },
    {
      "name": "Apoorva Singh",
      "email": "singhapoorva560@gmail.com"
    },
    {
      "name": "Himanshu Nirbhavane",
      "email": ""
    },
    {
      "name": "Anish Mondal",
      "email": "mondalanish677@gmail.com"
    },
    {
      "name": "Sumanta Barman",
      "email": "sumanrajroy96@gmail.com"
    },
    {
      "name": "Armika",
      "email": "sweccha777@gmail.com"
    },
    {
      "name": "Dinesh kumar",
      "email": "dineshkumarp446@gmail.com"
    },
    {
      "name": "Asma",
      "email": ""
    },
    {
      "name": "Sharon Mathew",
      "email": "sharonmaria542@gmail.com"
    },
    {
      "name": "Saiyyad Mohsim Anvarali",
      "email": "sayyedmohsin632@gmail.com"
    },
    {
      "name": "Akshay kumar",
      "email": "Babreakshaykumar@gmail.com"
    },
    {
      "name": "Akash Shukla",
      "email": ""
    },
    {
      "name": "Himana",
      "email": "himanasahib@gmail.com"
    },
    {
      "name": "Badige Manojkumar",
      "email": "mk1194695@gmail.com"
    },
    {
      "name": "Sakshi Kadam",
      "email": "sakshikadam3013@gmail.com"
    },
    {
      "name": "Baloram Chetry",
      "email": "baloramraut@yahoo.com"
    },
    {
      "name": "Nandini gangadhar swami",
      "email": "nandiniswami44@gmail.com"
    },
    {
      "name": "Abhay",
      "email": "abhay76689@gmail.com"
    },
    {
      "name": "Shibam Mascharak",
      "email": "shibammascharak@gmail.com"
    },
    {
      "name": "Rutik",
      "email": "rutik9377@gmail.com"
    },
    {
      "name": "Ramesh Gorain",
      "email": "gorainramesh20@gmail.com"
    },
    {
      "name": "Qazi",
      "email": "sturdystalwart17@gmail.com"
    },
    {
      "name": "Simran Gupta",
      "email": "simran109gupta@gmail.com"
    },
    {
      "name": "ABU SUFIYAN",
      "email": "abusufiyan786.007@gmail.com"
    },
    {
      "name": "Shreya Shaw",
      "email": ""
    },
    {
      "name": "Aditya Chakraborty",
      "email": "adityachakraborty847@gmail.com"
    },
    {
      "name": "Ashish dive",
      "email": "ashishdive821@gmail.com"
    },
    {
      "name": "Sajan Dulal",
      "email": "sajandulal0@gmail.com"
    },
    {
      "name": "Abid Mirza",
      "email": "mirzaabid957@gmail.com"
    },
    {
      "name": "Rick",
      "email": ""
    },
    {
      "name": "Chinmayee Sahoo",
      "email": "sahoochinmayee66@gmail.com"
    },
    {
      "name": "Vaishnavi gupta",
      "email": "guptavaishnavi062003@gmail.com"
    },
    {
      "name": "Nitin Mane",
      "email": "nitin.mane.entc.2023@gmail.com"
    },
    {
      "name": "Srikanth",
      "email": ""
    },
    {
      "name": "Meraj Ansari",
      "email": "merajansari56734@gmail.com"
    },
    {
      "name": "Naveentheja G",
      "email": "naveenthejchowdary@gmail.com"
    },
    {
      "name": "DURGESH SANJAY DEHLIWALE",
      "email": "durgeshdehliwale@gmail.com"
    },
    {
      "name": "Tejasvi pandey",
      "email": "kumaritejasvi9@gmail.com"
    },
    {
      "name": "VIVEK",
      "email": "aashuknnujiya@gmail.com"
    },
    {
      "name": "Sandhya Chittar",
      "email": "sandhyachittar1999@gmail.com"
    },
    {
      "name": "damini halwadiya",
      "email": "daminihalwadiya04@gmail.com"
    },
    {
      "name": "Ganesh Kumar",
      "email": "gk.legend@gmail.com"
    },
    {
      "name": "Balram",
      "email": ""
    },
    {
      "name": "aravind reddy",
      "email": "aravindragimakalapalli@gmail.com"
    },
    {
      "name": "Nayan Mandal",
      "email": "nayanmandal569@gmail.com"
    },
    {
      "name": "Monica",
      "email": "monicayadavr3@gmail.com"
    },
    {
      "name": "YESHASWINI B R",
      "email": "yeshaswinibryeshu@gmail.com"
    },
    {
      "name": "asif iqbal",
      "email": ""
    },
    {
      "name": "Ankit Chowdhury",
      "email": ""
    },
    {
      "name": "Priya Patil",
      "email": "patilpriya.1622@gmail.com"
    },
    {
      "name": "Omkar Nikam",
      "email": "omkarnikam2208@gmail.com"
    },
    {
      "name": "Saurabh",
      "email": "saurabhpisal2621@gmail.com"
    },
    {
      "name": "Swayam prakash",
      "email": "ggudu0782@gmil.com"
    },
    {
      "name": "Vinay K M",
      "email": "vkm80959@gmail.com"
    },
    {
      "name": "Avinash",
      "email": "akulal299@gmail.com"
    },
    {
      "name": "Sonal Vinay Patil",
      "email": "sonalvinaypatil2017@gmail.com"
    },
    {
      "name": "Krrish Jeswar",
      "email": "krrishjeswar01@gmail.com"
    },
    {
      "name": "Sayan Paul",
      "email": "sayanpaul2429@gmail.com"
    },
    {
      "name": "Akash Ramashray Thakur",
      "email": "akasht201109@gmail.com"
    },
    {
      "name": "Arun Kumar Ray",
      "email": "kumararun63075@gmail.com"
    },
    {
      "name": "Adil Siddiqui",
      "email": "bsharatsiddiq786@gmail.com"
    },
    {
      "name": "Ankit Kumar",
      "email": ""
    },
    {
      "name": "Saikat Samanta",
      "email": ""
    },
    {
      "name": "Dimple Uday nemade",
      "email": "nemadedimple0@gmail.com"
    },
    {
      "name": "Waquas Akhter",
      "email": "waquasakhter10@gmail.com"
    },
    {
      "name": "RAKHI SACHIN PAWAR",
      "email": "rakhipawar412@gmail.com"
    },
    {
      "name": "Subhajit",
      "email": ""
    },
    {
      "name": "RAJU RISHIDAS",
      "email": "rishi.itjgec@gmail.com"
    },
    {
      "name": "Khushal Vinod Pande",
      "email": "khushalpande2004@gmail.com"
    },
    {
      "name": "Pritam Mondal",
      "email": "PM071896@gmail.com"
    },
    {
      "name": "Sandeep",
      "email": "sand23270@gmail.com"
    },
    {
      "name": "surya pratap roy chowdhury",
      "email": "rc.susmita123@gmail.com"
    },
    {
      "name": "Vivek Kumar",
      "email": "vk262658@gmail.com"
    },
    {
      "name": "Ravi",
      "email": "sachinkasotiya2@gmail.com"
    },
    {
      "name": "Vjay",
      "email": ""
    },
    {
      "name": "Swati",
      "email": ""
    },
    {
      "name": "Kajal",
      "email": "suthar.kk29@gmail.com"
    },
    {
      "name": "Yash",
      "email": "gyash88322@gmail.com"
    },
    {
      "name": "Sarbajit Nandy",
      "email": "subhajitmandal985@gmail.com"
    },
    {
      "name": "Rasik Khamaria",
      "email": "khamariarasik58@gmail.com"
    },
    {
      "name": "Robin",
      "email": "deshwalrobin86@gmail.com"
    },
    {
      "name": "Rajeev Kumar",
      "email": "rajeev495442@gmail.com"
    },
    {
      "name": "Krishna Gutte",
      "email": "anandgutte123@gmail.com"
    },
    {
      "name": "Chaithra TG",
      "email": "tgchaithrashetty@gmail.com"
    },
    {
      "name": "Shubhadip Mondal",
      "email": "shubhadipm360@gmail.com"
    },
    {
      "name": "Saurabh Shinde",
      "email": ""
    },
    {
      "name": "Vivek Kumar ranjan",
      "email": "vivekkumaryadav8540@gmail.com"
    },
    {
      "name": "MD KAIF",
      "email": "kaifpanki786@gmail.com"
    },
    {
      "name": "MD. Shaquib",
      "email": ""
    },
    {
      "name": "Hasan",
      "email": "salauddinmuhammadalhasan@gmail.com"
    },
    {
      "name": "SAMIR KUMAR SHARMA",
      "email": "kypsdcdev@gmail.com"
    },
    {
      "name": "kinjol nandi",
      "email": ""
    },
    {
      "name": "Krish Patel",
      "email": "krishpatel0094@gmail.com"
    },
    {
      "name": "YANAMALA RAMU",
      "email": "ramuyanamala24@gmail.com"
    },
    {
      "name": "Ajay",
      "email": "ajaytiwari11012@gmail.com"
    },
    {
      "name": "siddhartha sarkar",
      "email": "siddharth8145@gmail.com"
    },
    {
      "name": "Srishti Kumari",
      "email": "srishtip103@gmail.com"
    },
    {
      "name": "Harsh",
      "email": "harsha.shinde5178@gmail.com"
    },
    {
      "name": "Apurva Ingavale",
      "email": "apurvasingavale17@gmail.com"
    },
    {
      "name": "Amruta Patil",
      "email": "amruta.patil7991@gmail.com"
    },
    {
      "name": "Balivada somanadh sandeep",
      "email": "somanadhsandeep333@gmail.com"
    },
    {
      "name": "Harish koda",
      "email": "harishkoda72@gmail.com"
    },
    {
      "name": "Christian",
      "email": "its21chrisdoms@gmail.com"
    },
    {
      "name": "Pranjal Pimple",
      "email": "pranjalpimple21@gmail.com"
    },
    {
      "name": "Sameer Kumar",
      "email": "sanjucst2006@gmail.com"
    },
    {
      "name": "krishnendu sarkar",
      "email": ""
    },
    {
      "name": "Sandhya Kumari",
      "email": "010205sandhya@gmail.com"
    },
    {
      "name": "ANSHU SEN",
      "email": ""
    },
    {
      "name": "Sayantan Podder",
      "email": "sayantanpodder82@gmail.com"
    },
    {
      "name": "Somavaar raj",
      "email": "sonamraj09092003@gmail.com"
    },
    {
      "name": "Yogesh v",
      "email": "vyogeshyoge@gmail.com"
    },
    {
      "name": "Jayesh Jadhav",
      "email": "jayeshvj077@gmail.com"
    },
    {
      "name": "Hritick singh",
      "email": "hriticksingh7595@gmail.com"
    },
    {
      "name": "Nitin meharoul",
      "email": "ginitin15@gmail.com"
    },
    {
      "name": "Pratik",
      "email": "pratikkhajinkar877@gmail.com"
    },
    {
      "name": "ROHIT KUMAR SAHA",
      "email": "rohitsaha534@gmail.com"
    },
    {
      "name": "Vishalakshi Sohani",
      "email": "vishalakshisohani99@gmail.com"
    },
    {
      "name": "Prashant",
      "email": "prashantsaraswat663@gmail.com"
    },
    {
      "name": "Akash Khedkar",
      "email": "akashkhedkar295@gmail.com"
    },
    {
      "name": "Anshu",
      "email": ""
    },
    {
      "name": "Vaibhav Bhirud",
      "email": ""
    },
    {
      "name": "Samriddhi",
      "email": "samriddhi822003@gmail.com"
    },
    {
      "name": "Ramchandra Mane",
      "email": "ram.mane181@gmail.com"
    },
    {
      "name": "Vipin Jain",
      "email": "vipinjain108@gmail.com"
    },
    {
      "name": "Jyoti kumari",
      "email": "jk073830@gmail.com"
    },
    {
      "name": "Hafizur",
      "email": ""
    },
    {
      "name": "Debabrata Sahu",
      "email": "sahudebabrata004@gmail.com"
    },
    {
      "name": "vivek patel",
      "email": "vsingh24509@gmail.com"
    },
    {
      "name": "Gopal",
      "email": "gautamgopal777@gmail.com"
    },
    {
      "name": "Hrushikesh Kadali",
      "email": "kadalihrushikesh2004@gmail.com"
    },
    {
      "name": "Dakshata Narendra ahire",
      "email": "ahiredakshata0@gmail.com"
    },
    {
      "name": "Krupal sudra",
      "email": "sudrakrupal02@gmail.com"
    },
    {
      "name": "smruti pruseth",
      "email": "kvsngsmruti27@gmail.com"
    },
    {
      "name": "Anisa",
      "email": "anibanu16@gmail.com"
    },
    {
      "name": "Sushil Shelke",
      "email": "shelke123sushil@gmail.com"
    },
    {
      "name": "Vidyashree",
      "email": "vidya6495h@gmail.com"
    },
    {
      "name": "hus",
      "email": "nsjfdks@gmail.com"
    },
    {
      "name": "Shreyas Som",
      "email": ""
    },
    {
      "name": "Nitin",
      "email": ""
    },
    {
      "name": "Nikhil Wagh",
      "email": ""
    },
    {
      "name": "Soham Sen",
      "email": "sen.soham24@gmail.com"
    },
    {
      "name": "Saurabh Dwivedi",
      "email": "saurabhdwivedi0707@gmail.com"
    },
    {
      "name": "Swati Verma",
      "email": "swativerma778899@gmail.com"
    },
    {
      "name": "Palasi Kumari",
      "email": ""
    },
    {
      "name": "Soubhik Das",
      "email": "draja2330@gmail.com"
    },
    {
      "name": "Rathna",
      "email": "acharyamanju547@gmail.com"
    },
    {
      "name": "Arif",
      "email": "garryostin47@gmail.com"
    },
    {
      "name": "Anup Biswas",
      "email": "anupbiswasseptember2006@gmail.com"
    },
    {
      "name": "JADHAV DARSHAN SANJAY",
      "email": "jadhavdarshan575@gmail.com"
    },
    {
      "name": "Nitish Kumar",
      "email": "nitishkr2242003@gmail.com"
    },
    {
      "name": "Ankit Raj",
      "email": "decankitsingh2003@gmail.com"
    },
    {
      "name": "Debayan Saha",
      "email": "debayansaha110@gmail.com"
    },
    {
      "name": "Aman jain",
      "email": "jainamanyt@gmail.com"
    },
    {
      "name": "Shivaraj",
      "email": "shivarajp224@gmail.com"
    },
    {
      "name": "Shashank",
      "email": "mamtha16mys@gmail.com"
    },
    {
      "name": "Tushar Bhagwan Patra",
      "email": "tusharpatra0312@gmail.com"
    },
    {
      "name": "Ram",
      "email": ""
    },
    {
      "name": "Rakesh Naskar",
      "email": ""
    },
    {
      "name": "Nikita",
      "email": ""
    },
    {
      "name": "Neha Chanda",
      "email": "Chandaneha1@gmail.com"
    },
    {
      "name": "Digambar Omprakash Purkar",
      "email": "digambarpurkar11@gmail.com"
    },
    {
      "name": "Prince Mishra",
      "email": "kumarroshansingh505@gmail.com"
    },
    {
      "name": "Mayur Bopche",
      "email": ""
    },
    {
      "name": "Deepak Das",
      "email": "deepakdas212004@gmail.com"
    },
    {
      "name": "Suhani",
      "email": "suhanisinghmuz707@gmail.com"
    },
    {
      "name": "Anil Yadav",
      "email": "anilyadav44x@gmail.com"
    },
    {
      "name": "Cidane Khumallambam",
      "email": "cidanekh@gmail.com"
    },
    {
      "name": "Sachin Kumar",
      "email": "kumarsachin72867@gmail.com"
    },
    {
      "name": "Neha Asutkar",
      "email": "asutkarneha44@gmail.com"
    },
    {
      "name": "Subhadip Adhikari",
      "email": ""
    },
    {
      "name": "Reshma Gopi",
      "email": "p.reshmagopi27@gmail.com"
    },
    {
      "name": "Suresh Kamat",
      "email": "sureshiitkamat@gmail.com"
    },
    {
      "name": "Prakash Biswas",
      "email": ""
    },
    {
      "name": "Steffy Fernando",
      "email": "alisfernando2004@gmail.com"
    },
    {
      "name": "Tulsi bedarkar",
      "email": "bedarkartrupti@gmail.com"
    },
    {
      "name": "Eti Patwari",
      "email": "etipatwari121@gmail.com"
    },
    {
      "name": "DEBJIT SAHA",
      "email": ""
    },
    {
      "name": "Praveen yadav",
      "email": "praveenyadav6833@gmail.com"
    },
    {
      "name": "Trilok Chand",
      "email": "trilok84@gmail.com"
    },
    {
      "name": "Aniket Kishor Yewale",
      "email": "aniketky2003@gmail.com"
    },
    {
      "name": "Jyotirmoy Debbarma",
      "email": "debbarma.j62@gmail.com"
    },
    {
      "name": "Avva naveen",
      "email": "avvanaveen.it@gmail.com"
    },
    {
      "name": "Jeet Chatterjee",
      "email": ""
    },
    {
      "name": "Sharanu m kalmani",
      "email": "sharanumk214@gmail.com"
    },
    {
      "name": "Pallavi Parshuram Kadukar",
      "email": "pallavikadukar571@gmail.com"
    },
    {
      "name": "Somenath Biswas",
      "email": ""
    },
    {
      "name": "Mohit Kumar",
      "email": "mohitkumar257s15@gmail.com"
    },
    {
      "name": "Yashika",
      "email": "kyashika.308@gmail.com"
    },
    {
      "name": "Anurag",
      "email": "sd8491535@gmail.com"
    },
    {
      "name": "Ankur Chakraborty",
      "email": "chakrabortyankur843@gmail.com"
    },
    {
      "name": "Satyam Bohit",
      "email": "bohitsatyam@gmail.com"
    },
    {
      "name": "Soma Das Manna",
      "email": "somadasmanna.03@gmail.com"
    },
    {
      "name": "ansh varshney",
      "email": "anshvar129@gmail.com"
    },
    {
      "name": "Pranav Parghi",
      "email": "neetaparghi@gmail.com"
    },
    {
      "name": "Vinay Kumar R",
      "email": "vinayvkr1812@gmail.com"
    },
    {
      "name": "Prosen Kumar Biswas",
      "email": "biswasprosenkumar@gmail.com"
    },
    {
      "name": "Sai Krishna",
      "email": "saikrishnavs2703@gmail.com"
    },
    {
      "name": "Himanshu jayant bhikule",
      "email": "bhikulej@gmail.com"
    },
    {
      "name": "Mohammad Mateen",
      "email": "mohamateen58@gmail.com"
    },
    {
      "name": "Sibram Badatya",
      "email": ""
    },
    {
      "name": "shantanu milind kedare",
      "email": "viju_kedare@yahoo.co.in"
    },
    {
      "name": "Rudranil Mallick",
      "email": "rudranilmallick8335@gmail.com"
    },
    {
      "name": "Rachana",
      "email": ""
    },
    {
      "name": "Sanchit Desai",
      "email": "sanchitdesai050@gmail.com"
    },
    {
      "name": "Jeyanth JM",
      "email": "jeyanthjm@gmail.com"
    },
    {
      "name": "khushali dhawde",
      "email": "642dhawde@gmail.com"
    },
    {
      "name": "Srilakshmi",
      "email": "srijaggu.11@gmail.com"
    },
    {
      "name": "Kunj Alpeshbhai Patel",
      "email": "kunj159ap@gmail.com"
    },
    {
      "name": "John Vesli",
      "email": "weslyj070@gmail.com"
    },
    {
      "name": "Waghchaure Shubhangi Ramnath",
      "email": "shubhangiwaghchaure50@gmail.com"
    },
    {
      "name": "Tushar Rajbanshi",
      "email": "tusharrajbanshi2.0@gmail.com"
    },
    {
      "name": "Komal zemase",
      "email": "komalzemase2016@gmail.com"
    },
    {
      "name": "Sanskruti\tdubey",
      "email": "dubeysanskruti93@gmail.com"
    },
    {
      "name": "RAZAQ",
      "email": "rrazaq081@gmail.com"
    },
    {
      "name": "Aditya Ganguly",
      "email": "adityagdelete@gmail.com"
    },
    {
      "name": "Shruti sonawane",
      "email": "sonawaneshruti360@gmail.com"
    },
    {
      "name": "SIDDHI VAGAL",
      "email": "siddhivagal90@gmail.com"
    },
    {
      "name": "Barsha D",
      "email": ""
    },
    {
      "name": "Sushant salunkhe",
      "email": ""
    },
    {
      "name": "Abhishek Sable",
      "email": "abhisheksable380@gmail.com"
    },
    {
      "name": "Harshit Turkar",
      "email": "harshturkar99@gmail.com"
    },
    {
      "name": "Vishal",
      "email": ""
    },
    {
      "name": "subhodip sardar",
      "email": ""
    },
    {
      "name": "Kinshuk",
      "email": ""
    },
    {
      "name": "Rohit",
      "email": ""
    },
    {
      "name": "Raunak Singh",
      "email": ""
    },
    {
      "name": "Prince",
      "email": ""
    },
    {
      "name": "Chethankumar",
      "email": ""
    },
    {
      "name": "ATHARVA BADHE",
      "email": ""
    },
    {
      "name": "Pratima Mishra",
      "email": ""
    },
    {
      "name": "Akanksha Rajendra Nawale",
      "email": "akankshanawale2004@gmail.com"
    },
    {
      "name": "Subham SIngha",
      "email": ""
    },
    {
      "name": "Prachi Chavan",
      "email": ""
    },
    {
      "name": "Sanchari Ghosh",
      "email": ""
    },
    {
      "name": "Insha",
      "email": ""
    },
    {
      "name": "SHREYAS",
      "email": ""
    },
    {
      "name": "Melita Sandy",
      "email": ""
    },
    {
      "name": "Yupdil",
      "email": "mohitpawar2k2k@gmail.com"
    },
    {
      "name": "Manish Pednekar",
      "email": "pednekarmanish349@gmail.com"
    },
    {
      "name": "Vaibhav Pushkarna",
      "email": ""
    },
    {
      "name": "Ramkishor",
      "email": ""
    },
    {
      "name": "Indranil Pathak",
      "email": ""
    },
    {
      "name": "Lokesh",
      "email": ""
    },
    {
      "name": "Priyankar Samanta",
      "email": ""
    },
    {
      "name": "Raman Sahay",
      "email": "raman334sahay@gmail.com"
    },
    {
      "name": "Isha Ball",
      "email": "ishaball137@gmail.com"
    },
    {
      "name": "Komal Giri",
      "email": ""
    },
    {
      "name": "Mehak Prasad",
      "email": "mehakprasad2004@gmail.com"
    },
    {
      "name": "Ruksar Fathima",
      "email": ""
    },
    {
      "name": "avijit maity",
      "email": "avijitmaity146@gmail.com"
    },
    {
      "name": "ajitesh kumar yadav",
      "email": "ajiteshy30@gmail.com"
    },
    {
      "name": "Monu Verma",
      "email": "monuverma0759@gmail.com"
    },
    {
      "name": "DARSHAN JADHAV",
      "email": ""
    },
    {
      "name": "Sayan Das",
      "email": ""
    },
    {
      "name": "Manav Vithalani",
      "email": "deanwinchesterdark@proton.me"
    },
    {
      "name": "Rajesh Ambre/ Shaksham Ambre",
      "email": ""
    },
    {
      "name": "Bapi Paul",
      "email": "palbapi577@gmail.com"
    },
    {
      "name": "Soumajit Bhattacharjee",
      "email": "rudrasoumya1998@gmail.com"
    },
    {
      "name": "Fardeen",
      "email": ""
    },
    {
      "name": "Kshtriya Raj Singh",
      "email": ""
    },
    {
      "name": "Surojit Sardar",
      "email": "Surojitarijit@gmail.com"
    },
    {
      "name": "Shaik Basha",
      "email": "bashamohammad12963@gmail.com"
    },
    {
      "name": "Sudipto Paul",
      "email": "paulsudipto655@gmail.com"
    },
    {
      "name": "Sajid Ahmad",
      "email": "sajidahmad000@gmail.com"
    },
    {
      "name": "PRIYOTOSH MEDDYA",
      "email": ""
    },
    {
      "name": "Mohit Vaghela",
      "email": ""
    },
    {
      "name": "Amit Mondal",
      "email": ""
    },
    {
      "name": "Md Samir",
      "email": "mdsamirali444s@gmail.com"
    },
    {
      "name": "Vinayaka B",
      "email": "vinayakab825@gmail.com"
    },
    {
      "name": "Piyush Sharma",
      "email": ""
    },
    {
      "name": "Ramakant",
      "email": "ramakanta.voltech@gmail.com"
    },
    {
      "name": "Pritam paul",
      "email": "pritampaul659@gmail.com"
    },
    {
      "name": "Indranil Sarkar",
      "email": "indranilsarkar.bkp@gmail.com"
    },
    {
      "name": "Aritra Paul",
      "email": "paularitra527@gmail.com"
    },
    {
      "name": "Subhodeep Mondal",
      "email": "subhodeep14196@gmail.com"
    },
    {
      "name": "Payel Ray",
      "email": ""
    },
    {
      "name": "Deeksha",
      "email": "deekshaoberoi100@gmail.com"
    },
    {
      "name": "Vishnu prasad",
      "email": "vishnuprasad9061484957@gmail.com"
    },
    {
      "name": "Amit Kumar",
      "email": "akmyamit4@gmail.com"
    },
    {
      "name": "Aritra Chakraborty",
      "email": "aritrachakraborty@gmail.com"
    },
    {
      "name": "Manish Gupta",
      "email": "gupta35.manish@gmail.com"
    },
    {
      "name": "Anurag Nath",
      "email": "bittunath4321@gmail.com"
    },
    {
      "name": "Meghana",
      "email": ""
    },
    {
      "name": "Subhasish Dey",
      "email": ""
    },
    {
      "name": "Navanath",
      "email": "nava797295@gmail.com"
    },
    {
      "name": "Ayesha Shaikh",
      "email": "39ayeshhha@gmail.com"
    },
    {
      "name": "Somenath",
      "email": ""
    },
    {
      "name": "Sukanta mitra",
      "email": "significant.sm@gmail.com"
    },
    {
      "name": "Devorima Bakshi",
      "email": "devorimabakshi12@gmail.com"
    },
    {
      "name": "MOHIT kakade",
      "email": "kakademohit10@gmail.com"
    },
    {
      "name": "Surdas puthem",
      "email": "surdas.4767puthem@gmail.com"
    },
    {
      "name": "Anurag sharma",
      "email": "superstar.king.md@gmail.com"
    },
    {
      "name": "ramgopal",
      "email": "akshuinstagramuser@gmail.com"
    },
    {
      "name": "Harshal Desale",
      "email": "harshaldesale370@gmail.com"
    },
    {
      "name": "Nilesh Jain",
      "email": "nileshjain212@gmail.com"
    },
    {
      "name": "Yashita Pachauri",
      "email": "yashpach2003@gmail.com"
    },
    {
      "name": "Vachanashri.M.M",
      "email": "vachanashrimm@gmail.com"
    },
    {
      "name": "Chandu M",
      "email": "chanduak99@gmil.com"
    },
    {
      "name": "Deepa",
      "email": "dd940095@gmail.com"
    },
    {
      "name": "Pratik Prashant Bhalme",
      "email": "pratikbhalme16@gmail.com"
    },
    {
      "name": "Abhishek Sannigrahi",
      "email": "abhisheksannigrahi827@gmail.com"
    },
    {
      "name": "Tuhin Biswas",
      "email": ""
    },
    {
      "name": "Jotish Sarkar",
      "email": "jotishsarkar1119@gmail.com"
    },
    {
      "name": "Annu ambedkar",
      "email": "annuambedkar81@gmail.com"
    },
    {
      "name": "Anurag Kumar",
      "email": "ak8694485@gmail.com"
    },
    {
      "name": "Simran Simran",
      "email": ""
    },
    {
      "name": "Krishna Jatiya",
      "email": "krishnajatiya16@gmail.com"
    },
    {
      "name": "Brajesh Kumar Pandey",
      "email": "brajesh.esab@gmail.com"
    },
    {
      "name": "SIBAYAN CHAKRABORTY",
      "email": "sibayan87@outlook.com"
    },
    {
      "name": "Abhishek Mishra",
      "email": ""
    },
    {
      "name": "Ravi gaikwad",
      "email": "Gaikwadravindra2696@gmail.com"
    },
    {
      "name": "Pinaki Ghosh",
      "email": "gpinaki508@gmail.com"
    },
    {
      "name": "Deep chakraborty",
      "email": "deeparatychakraborty@gmail.com"
    },
    {
      "name": "Yuvraj Raja",
      "email": "yr283941@gmail.com"
    },
    {
      "name": "Binay Kr Prasad",
      "email": "binaykrprasad027@gmail.com"
    },
    {
      "name": "Vaidehi Gupta",
      "email": "ayushigupta875648@gmail.com"
    },
    {
      "name": "Saipayan Banerjee",
      "email": "Banerjeesaipayan35@gmail.com"
    },
    {
      "name": "Rakesh Baidya",
      "email": "rakeshbaidya031@gmail.com"
    },
    {
      "name": "Varad",
      "email": "varadgampawar7@gmail.com"
    },
    {
      "name": "Alok Mahato",
      "email": "mahatoalok522@gmail.com"
    },
    {
      "name": "Soumyadip Das",
      "email": "dassoumyadip440@gmail.com"
    },
    {
      "name": "Deepak kumar rana",
      "email": "deepakkumarrana312@gmail.com"
    },
    {
      "name": "Subhadip Manna",
      "email": "msubhadip703@gmail.com"
    },
    {
      "name": "Raju Das",
      "email": ""
    },
    {
      "name": "S dileep kumar",
      "email": "dileepsdk030@gmail.com"
    },
    {
      "name": "Rahul",
      "email": ""
    },
    {
      "name": "Debanjan Chatterjee",
      "email": "Chatterjee2001debanjan@gmail.com"
    },
    {
      "name": "Asad Ali",
      "email": ""
    },
    {
      "name": "Unmona Tamuli",
      "email": "unmonatamuli@gmail.com"
    }
   ]